cisdb/__init__.py
cisdb/_version.py
cisdb/channelrow.py
cisdb/channeltable.py
cisdb/cis.py
cisdb/descriptionrow.py
cisdb/descriptionstable.py
cisdb/fragmentrow.py
cisdb/fragmenttable.py
cisdb/iforow.py
cisdb/ifotable.py
cisdb/UnitTests/__init__.py
cisdb/UnitTests/pytest.ini
cisdb/UnitTests/test_channeltable.py
cisdb/UnitTests/test_column.py
cisdb/UnitTests/test_database.py
cisdb/UnitTests/test_fragmenttable.py
cisdb/UnitTests/test_table.py
cisdb/cli/__init__.py
cisdb/cli/copy_old_desc.py
cisdb/cli/update_chan_nds.py
cisdb/cli/update_from_frames.py
cisdb/cli/update_ifo_fragments.py
cisdb/etc/cisdb.ini
cisdb/web/channel_search_web.py
cisdb-0.0.7.dist-info/LICENSE.txt
cisdb-0.0.7.dist-info/METADATA
cisdb-0.0.7.dist-info/WHEEL
cisdb-0.0.7.dist-info/entry_points.txt
cisdb-0.0.7.dist-info/top_level.txt
cisdb-0.0.7.dist-info/RECORD
